odoo/addons/website_sale_wishlist_keep/README.rst
odoo/addons/website_sale_wishlist_keep/__init__.py
odoo/addons/website_sale_wishlist_keep/__manifest__.py
odoo/addons/website_sale_wishlist_keep/i18n/ca.po
odoo/addons/website_sale_wishlist_keep/i18n/es.po
odoo/addons/website_sale_wishlist_keep/i18n/fr.po
odoo/addons/website_sale_wishlist_keep/i18n/nl.po
odoo/addons/website_sale_wishlist_keep/i18n/website_sale_wishlist_keep.pot
odoo/addons/website_sale_wishlist_keep/readme/CONTRIBUTORS.rst
odoo/addons/website_sale_wishlist_keep/readme/DESCRIPTION.rst
odoo/addons/website_sale_wishlist_keep/readme/USAGE.rst
odoo/addons/website_sale_wishlist_keep/static/description/icon.png
odoo/addons/website_sale_wishlist_keep/static/description/index.html
odoo/addons/website_sale_wishlist_keep/static/src/js/tour.js
odoo/addons/website_sale_wishlist_keep/templates/assets.xml
odoo/addons/website_sale_wishlist_keep/tests/__init__.py
odoo/addons/website_sale_wishlist_keep/tests/test_ui.py
odoo/addons/website_sale_wishlist_keep/views/website_sale_wishlist_template.xml
odoo13_addon_website_sale_wishlist_keep-13.0.1.0.1.dev5.dist-info/METADATA
odoo13_addon_website_sale_wishlist_keep-13.0.1.0.1.dev5.dist-info/WHEEL
odoo13_addon_website_sale_wishlist_keep-13.0.1.0.1.dev5.dist-info/top_level.txt
odoo13_addon_website_sale_wishlist_keep-13.0.1.0.1.dev5.dist-info/RECORD
